xarray_graph-2024.9.1.dist-info/METADATA
xarray_graph-2024.9.1.dist-info/WHEEL
xarray_graph-2024.9.1.dist-info/entry_points.txt
xarray_graph-2024.9.1.dist-info/licenses/LICENSE
xarray_graph/XarrayGraph copy.py
xarray_graph/XarrayGraph.py
xarray_graph/__init__.py
xarray_graph/__main__.py
xarray_graph/heka_reader.py
xarray_graph/io.py
xarray_graph/tmp/RegionsManager.py
xarray_graph-2024.9.1.dist-info/RECORD
